qpyt/ComPort.py
qpyt/Project.py
qpyt/ReplFileOps.py
qpyt/ReplTerminal.py
qpyt/Runtime.py
qpyt/SocketServer.py
qpyt/__init__.py
qpyt/cli.py
qpyt/boards/Board_EG91X.py
qpyt-0.3.2.dist-info/METADATA
qpyt-0.3.2.dist-info/WHEEL
qpyt-0.3.2.dist-info/entry_points.txt
qpyt-0.3.2.dist-info/RECORD
