Metadata-Version: 2.4
Name: qpyt
Version: 0.3.2
Summary: CLI tool for QuecPython rapid development
Author-email: Günter Prossliner <6724584+gprossliner@users.noreply.github.com>
License-Expression: MIT
Classifier: Operating System :: OS Independent
Classifier: Programming Language :: Python :: 3
Requires-Python: >=3.11
Requires-Dist: mpy-cross==1.12
Requires-Dist: pyserial>=3.5
Requires-Dist: pyyaml>=6.0
Requires-Dist: watchfiles>=0.18.0
